pytracks/__init__.py
pytracks/counting.py
pytracks/dating.py
pytracks/labeling.py
pytracks/measuring.py
pytracks/misc.py
pytracks/preproc.py
pytracks/processing.py
pytracks/setup.py
pytracks/skeletonization_method.py
pytracks/test.py
pytracks/tools.py
pytracks-0.0.1a1.dist-info/LICENSE
pytracks-0.0.1a1.dist-info/METADATA
pytracks-0.0.1a1.dist-info/WHEEL
pytracks-0.0.1a1.dist-info/top_level.txt
pytracks-0.0.1a1.dist-info/RECORD
