Metadata-Version: 2.1
Name: pytracks
Version: 0.0.1a1
Summary: pytracks: Acquiring fission-tracks using image processing
Home-page: https://github.com/pytracks/pytracks
Author: Alexandre Fioravante de Siqueira
Author-email: afdesiqueira@gmail.com
License: UNKNOWN
Platform: UNKNOWN
Classifier: Development Status :: 3 - Alpha
Classifier: Programming Language :: Python :: 3
Classifier: License :: OSI Approved :: GNU General Public License v3 or later (GPLv3+)
Classifier: Operating System :: OS Independent
Requires-Dist: dtcwt
Requires-Dist: matplotlib
Requires-Dist: numpy
Requires-Dist: scipy
Requires-Dist: skimage
